rock_paper_scissors/__init__.py
rock_paper_scissors/rock_paper_scissors.py
py_rps_game-1.0.dist-info/LICENSE
py_rps_game-1.0.dist-info/METADATA
py_rps_game-1.0.dist-info/WHEEL
py_rps_game-1.0.dist-info/entry_points.txt
py_rps_game-1.0.dist-info/top_level.txt
py_rps_game-1.0.dist-info/RECORD
